{
  "schema_version": "1.0",
  "generated_at": "2026-01-02T20:58:30.415Z",
  "pairs": {
    "clothes:Wizard Drip||facewear:Cool Glasses": [
      "3740",
      "2543",
      "1833",
      "12",
      "2997",
      "3191",
      "2525"
    ],
    "base:Wojak||facewear:Matrix Lenses": [
      "43",
      "427",
      "1016",
      "560",
      "724",
      "860",
      "658",
      "706",
      "1092",
      "612",
      "664",
      "825",
      "762",
      "1303",
      "228",
      "647",
      "319",
      "1113",
      "604",
      "795",
      "202",
      "782",
      "15",
      "541",
      "868",
      "638",
      "1725",
      "930",
      "569",
      "1403",
      "120",
      "949",
      "594",
      "259",
      "1437",
      "1890",
      "149",
      "1078",
      "579",
      "1625",
      "362",
      "817",
      "1606",
      "1279",
      "774",
      "75",
      "329",
      "1840",
      "1194",
      "1491",
      "688",
      "369",
      "1000",
      "850",
      "303",
      "130",
      "485",
      "1325",
      "1339",
      "911",
      "1959",
      "81",
      "1165",
      "1263",
      "1044",
      "1671",
      "166",
      "1219",
      "343",
      "890",
      "1232",
      "1455",
      "243",
      "1569",
      "892",
      "411",
      "521",
      "1905",
      "1181",
      "93",
      "838",
      "1057",
      "1134",
      "1923",
      "463",
      "1252",
      "1352",
      "1205",
      "622",
      "1784",
      "285",
      "1549"
    ],
    "face:NPC||mouth:Hannibal Mask": [
      "41",
      "309",
      "1857",
      "870"
    ],
    "face:NPC||facewear:Wizard Glasses": [
      "41",
      "2540",
      "592",
      "732",
      "2067",
      "548",
      "1858",
      "1854"
    ],
    "facewear:No Face Wear||head:2Pac Bandana": [
      "3492",
      "3711",
      "42",
      "3567",
      "330",
      "350",
      "1940",
      "1319",
      "746"
    ],
    "facewear:MOG Glasses||mouth:Numb": [
      "3260",
      "3886",
      "3344",
      "3329",
      "1847",
      "4128",
      "1091",
      "3650",
      "3256",
      "3224",
      "707",
      "76",
      "2253",
      "2644",
      "1600",
      "1510",
      "2193",
      "902",
      "519",
      "2324",
      "2952",
      "1777",
      "1032",
      "99",
      "1894",
      "1326",
      "1451",
      "1872",
      "891"
    ],
    "clothes:Bepe Suit||face:Terminator": [
      "2108",
      "3713",
      "3916",
      "3010",
      "167",
      "2763",
      "168",
      "2107",
      "2105",
      "2106"
    ],
    "clothes:Pepe Suit||mouth:Numb": [
      "2144",
      "2141",
      "191",
      "2146"
    ],
    "clothes:SWAT Gear||head:Military Beret": [
      "3877",
      "3764",
      "3864",
      "3978",
      "3121",
      "2905",
      "3122",
      "2361",
      "2906",
      "493",
      "3120",
      "192"
    ],
    "facewear:MOG Glasses||mouth:Pipe": [
      "3879",
      "3928",
      "2769",
      "3768",
      "2461",
      "456",
      "245",
      "1357",
      "2134",
      "1323",
      "1415",
      "1665",
      "1340",
      "841",
      "763"
    ],
    "clothes:Proof of Prayer||mouth:Bandana Mask": [
      "3530",
      "3284",
      "276"
    ],
    "clothes:Viking Armor||facewear:Wizard Glasses": [
      "2183",
      "443",
      "421"
    ],
    "clothes:Firefighter Uniform||head:Centurion": [
      "539"
    ],
    "clothes:Super Saiyan Uniform||head:Construction Helmet": [
      "3354",
      "3605",
      "911",
      "2701",
      "924"
    ],
    "clothes:Ninja Turtle Fit||head:Ronin Helmet": [
      "970",
      "999"
    ],
    "clothes:Bepe Army||head:Firefighter Helmet": [
      "3468",
      "4032",
      "2570",
      "1195",
      "1137",
      "1166"
    ],
    "clothes:Born to Ride||facewear:Eye Patch": [
      "2770",
      "2581",
      "1276",
      "1229",
      "2584",
      "1249"
    ],
    "clothes:Topless||facewear:Cyber Shades": [
      "4003",
      "3623",
      "3409",
      "3390",
      "3413",
      "2417",
      "1611",
      "1536",
      "1574",
      "1555"
    ],
    "face:Bleeding Bags||head:Ronin Helmet": [
      "3299",
      "3300",
      "3544",
      "3480",
      "3977",
      "3578",
      "3326",
      "3259",
      "3432",
      "1960",
      "3426"
    ],
    "clothes:Pepe Suit||mouth:Pipe": [
      "3074",
      "2143",
      "2134"
    ],
    "clothes:Pepe Suit||facewear:VR Headset": [
      "3958",
      "2144"
    ],
    "clothes:Denim Vest||facewear:Night Vision": [
      "3038",
      "2792"
    ],
    "clothes:God's Robe||head:Twin Braids": [
      "2809"
    ],
    "base:Waifu||clothes:Suit": [
      "2955",
      "2960",
      "2958",
      "2959",
      "2953",
      "2957",
      "2956",
      "2961",
      "2954",
      "2952",
      "2951"
    ],
    "facewear:Aviators||head:Tiara": [
      "3064"
    ],
    "base:Monkey Zoo||mouth:Bandana Mask": [
      "3468",
      "3491",
      "3502",
      "3496",
      "3557",
      "3643",
      "3484",
      "3590",
      "3530",
      "3631"
    ],
    "base:Alien Wojak||facewear:Cool Glasses": [
      "3672"
    ],
    "head:Piccolo Turban||mouth:Numb": [
      "3703",
      "3706"
    ],
    "facewear:Cyber Shades||head:Standard Cut": [
      "3769"
    ],
    "base:Bepe Soyjak||clothes:Goose Suit": [
      "4055",
      "4056"
    ]
  }
}
